{"nodes": [{"id": "plot_analysis", "label": "plot_analysis.py", "file_type": "code", "source_file": "data analysis/pythonscripts/plot_analysis.py", "source_location": null, "source_url": null, "captured_at": null, "author": null, "contributor": null}], "edges": [{"source": "plot_analysis", "target": "randomness_results", "relation": "references", "confidence": "EXTRACTED", "confidence_score": 1.0, "source_file": "data analysis/pythonscripts/plot_analysis.py", "source_location": null, "weight": 1.0}, {"source": "plot_analysis", "target": "random_values_csv", "relation": "references", "confidence": "EXTRACTED", "confidence_score": 1.0, "source_file": "data analysis/pythonscripts/plot_analysis.py", "source_location": null, "weight": 1.0}], "hyperedges": []}