{"nodes": [{"id": "c_users_vince_projects_prng_pio_libdeps_feather_m4_adafruit_epd_src_drivers_adafruit_ssd1680_cpp", "label": "Adafruit_SSD1680.cpp", "file_type": "code", "source_file": "C:\\Users\\vince\\Projects\\PRNG\\.pio\\libdeps\\feather_m4\\Adafruit EPD\\src\\drivers\\Adafruit_SSD1680.cpp", "source_location": "L1"}, {"id": "drivers_adafruit_ssd1680_adafruit_ssd1680", "label": "Adafruit_SSD1680()", "file_type": "code", "source_file": "C:\\Users\\vince\\Projects\\PRNG\\.pio\\libdeps\\feather_m4\\Adafruit EPD\\src\\drivers\\Adafruit_SSD1680.cpp", "source_location": "L43"}, {"id": "drivers_adafruit_ssd1680_busy_wait", "label": "busy_wait()", "file_type": "code", "source_file": "C:\\Users\\vince\\Projects\\PRNG\\.pio\\libdeps\\feather_m4\\Adafruit EPD\\src\\drivers\\Adafruit_SSD1680.cpp", "source_location": "L111"}, {"id": "drivers_adafruit_ssd1680_begin", "label": "begin()", "file_type": "code", "source_file": "C:\\Users\\vince\\Projects\\PRNG\\.pio\\libdeps\\feather_m4\\Adafruit EPD\\src\\drivers\\Adafruit_SSD1680.cpp", "source_location": "L127"}, {"id": "drivers_adafruit_ssd1680_update", "label": "update()", "file_type": "code", "source_file": "C:\\Users\\vince\\Projects\\PRNG\\.pio\\libdeps\\feather_m4\\Adafruit EPD\\src\\drivers\\Adafruit_SSD1680.cpp", "source_location": "L139"}, {"id": "drivers_adafruit_ssd1680_powerup", "label": "powerUp()", "file_type": "code", "source_file": "C:\\Users\\vince\\Projects\\PRNG\\.pio\\libdeps\\feather_m4\\Adafruit EPD\\src\\drivers\\Adafruit_SSD1680.cpp", "source_location": "L157"}, {"id": "drivers_adafruit_ssd1680_powerdown", "label": "powerDown()", "file_type": "code", "source_file": "C:\\Users\\vince\\Projects\\PRNG\\.pio\\libdeps\\feather_m4\\Adafruit EPD\\src\\drivers\\Adafruit_SSD1680.cpp", "source_location": "L205"}, {"id": "drivers_adafruit_ssd1680_writeramcommand", "label": "writeRAMCommand()", "file_type": "code", "source_file": "C:\\Users\\vince\\Projects\\PRNG\\.pio\\libdeps\\feather_m4\\Adafruit EPD\\src\\drivers\\Adafruit_SSD1680.cpp", "source_location": "L228"}, {"id": "drivers_adafruit_ssd1680_setramaddress", "label": "setRAMAddress()", "file_type": "code", "source_file": "C:\\Users\\vince\\Projects\\PRNG\\.pio\\libdeps\\feather_m4\\Adafruit EPD\\src\\drivers\\Adafruit_SSD1680.cpp", "source_location": "L245"}], "edges": [{"source": "c_users_vince_projects_prng_pio_libdeps_feather_m4_adafruit_epd_src_drivers_adafruit_ssd1680_cpp", "target": "c_users_vince_projects_prng_pio_libdeps_feather_m4_adafruit_epd_src_drivers_adafruit_ssd1680_h", "relation": "imports", "context": "import", "confidence": "EXTRACTED", "source_file": "C:\\Users\\vince\\Projects\\PRNG\\.pio\\libdeps\\feather_m4\\Adafruit EPD\\src\\drivers\\Adafruit_SSD1680.cpp", "source_location": "L1", "weight": 1.0}, {"source": "c_users_vince_projects_prng_pio_libdeps_feather_m4_adafruit_epd_src_drivers_adafruit_ssd1680_cpp", "target": "adafruit_epd", "relation": "imports", "context": "import", "confidence": "EXTRACTED", "source_file": "C:\\Users\\vince\\Projects\\PRNG\\.pio\\libdeps\\feather_m4\\Adafruit EPD\\src\\drivers\\Adafruit_SSD1680.cpp", "source_location": "L3", "weight": 1.0}, {"source": "c_users_vince_projects_prng_pio_libdeps_feather_m4_adafruit_epd_src_drivers_adafruit_ssd1680_cpp", "target": "drivers_adafruit_ssd1680_adafruit_ssd1680", "relation": "contains", "confidence": "EXTRACTED", "source_file": "C:\\Users\\vince\\Projects\\PRNG\\.pio\\libdeps\\feather_m4\\Adafruit EPD\\src\\drivers\\Adafruit_SSD1680.cpp", "source_location": "L43", "weight": 1.0}, {"source": "c_users_vince_projects_prng_pio_libdeps_feather_m4_adafruit_epd_src_drivers_adafruit_ssd1680_cpp", "target": "drivers_adafruit_ssd1680_adafruit_ssd1680", "relation": "contains", "confidence": "EXTRACTED", "source_file": "C:\\Users\\vince\\Projects\\PRNG\\.pio\\libdeps\\feather_m4\\Adafruit EPD\\src\\drivers\\Adafruit_SSD1680.cpp", "source_location": "L82", "weight": 1.0}, {"source": "c_users_vince_projects_prng_pio_libdeps_feather_m4_adafruit_epd_src_drivers_adafruit_ssd1680_cpp", "target": "drivers_adafruit_ssd1680_busy_wait", "relation": "contains", "confidence": "EXTRACTED", "source_file": "C:\\Users\\vince\\Projects\\PRNG\\.pio\\libdeps\\feather_m4\\Adafruit EPD\\src\\drivers\\Adafruit_SSD1680.cpp", "source_location": "L111", "weight": 1.0}, {"source": "c_users_vince_projects_prng_pio_libdeps_feather_m4_adafruit_epd_src_drivers_adafruit_ssd1680_cpp", "target": "drivers_adafruit_ssd1680_begin", "relation": "contains", "confidence": "EXTRACTED", "source_file": "C:\\Users\\vince\\Projects\\PRNG\\.pio\\libdeps\\feather_m4\\Adafruit EPD\\src\\drivers\\Adafruit_SSD1680.cpp", "source_location": "L127", "weight": 1.0}, {"source": "c_users_vince_projects_prng_pio_libdeps_feather_m4_adafruit_epd_src_drivers_adafruit_ssd1680_cpp", "target": "drivers_adafruit_ssd1680_update", "relation": "contains", "confidence": "EXTRACTED", "source_file": "C:\\Users\\vince\\Projects\\PRNG\\.pio\\libdeps\\feather_m4\\Adafruit EPD\\src\\drivers\\Adafruit_SSD1680.cpp", "source_location": "L139", "weight": 1.0}, {"source": "c_users_vince_projects_prng_pio_libdeps_feather_m4_adafruit_epd_src_drivers_adafruit_ssd1680_cpp", "target": "drivers_adafruit_ssd1680_powerup", "relation": "contains", "confidence": "EXTRACTED", "source_file": "C:\\Users\\vince\\Projects\\PRNG\\.pio\\libdeps\\feather_m4\\Adafruit EPD\\src\\drivers\\Adafruit_SSD1680.cpp", "source_location": "L157", "weight": 1.0}, {"source": "c_users_vince_projects_prng_pio_libdeps_feather_m4_adafruit_epd_src_drivers_adafruit_ssd1680_cpp", "target": "drivers_adafruit_ssd1680_powerdown", "relation": "contains", "confidence": "EXTRACTED", "source_file": "C:\\Users\\vince\\Projects\\PRNG\\.pio\\libdeps\\feather_m4\\Adafruit EPD\\src\\drivers\\Adafruit_SSD1680.cpp", "source_location": "L205", "weight": 1.0}, {"source": "c_users_vince_projects_prng_pio_libdeps_feather_m4_adafruit_epd_src_drivers_adafruit_ssd1680_cpp", "target": "drivers_adafruit_ssd1680_writeramcommand", "relation": "contains", "confidence": "EXTRACTED", "source_file": "C:\\Users\\vince\\Projects\\PRNG\\.pio\\libdeps\\feather_m4\\Adafruit EPD\\src\\drivers\\Adafruit_SSD1680.cpp", "source_location": "L228", "weight": 1.0}, {"source": "c_users_vince_projects_prng_pio_libdeps_feather_m4_adafruit_epd_src_drivers_adafruit_ssd1680_cpp", "target": "drivers_adafruit_ssd1680_setramaddress", "relation": "contains", "confidence": "EXTRACTED", "source_file": "C:\\Users\\vince\\Projects\\PRNG\\.pio\\libdeps\\feather_m4\\Adafruit EPD\\src\\drivers\\Adafruit_SSD1680.cpp", "source_location": "L245", "weight": 1.0}, {"source": "drivers_adafruit_ssd1680_begin", "target": "drivers_adafruit_ssd1680_powerdown", "relation": "calls", "context": "call", "confidence": "EXTRACTED", "source_file": "C:\\Users\\vince\\Projects\\PRNG\\.pio\\libdeps\\feather_m4\\Adafruit EPD\\src\\drivers\\Adafruit_SSD1680.cpp", "source_location": "L131", "weight": 1.0}, {"source": "drivers_adafruit_ssd1680_update", "target": "drivers_adafruit_ssd1680_busy_wait", "relation": "calls", "context": "call", "confidence": "EXTRACTED", "source_file": "C:\\Users\\vince\\Projects\\PRNG\\.pio\\libdeps\\feather_m4\\Adafruit EPD\\src\\drivers\\Adafruit_SSD1680.cpp", "source_location": "L145", "weight": 1.0}, {"source": "drivers_adafruit_ssd1680_powerup", "target": "drivers_adafruit_ssd1680_busy_wait", "relation": "calls", "context": "call", "confidence": "EXTRACTED", "source_file": "C:\\Users\\vince\\Projects\\PRNG\\.pio\\libdeps\\feather_m4\\Adafruit EPD\\src\\drivers\\Adafruit_SSD1680.cpp", "source_location": "L162", "weight": 1.0}, {"source": "drivers_adafruit_ssd1680_powerdown", "target": "drivers_adafruit_ssd1680_busy_wait", "relation": "calls", "context": "call", "confidence": "EXTRACTED", "source_file": "C:\\Users\\vince\\Projects\\PRNG\\.pio\\libdeps\\feather_m4\\Adafruit EPD\\src\\drivers\\Adafruit_SSD1680.cpp", "source_location": "L215", "weight": 1.0}], "raw_calls": [{"caller_nid": "drivers_adafruit_ssd1680_adafruit_ssd1680", "callee": "malloc", "is_member_call": false, "source_file": "C:\\Users\\vince\\Projects\\PRNG\\.pio\\libdeps\\feather_m4\\Adafruit EPD\\src\\drivers\\Adafruit_SSD1680.cpp", "source_location": "L61"}, {"caller_nid": "drivers_adafruit_ssd1680_adafruit_ssd1680", "callee": "malloc", "is_member_call": false, "source_file": "C:\\Users\\vince\\Projects\\PRNG\\.pio\\libdeps\\feather_m4\\Adafruit EPD\\src\\drivers\\Adafruit_SSD1680.cpp", "source_location": "L62"}, {"caller_nid": "drivers_adafruit_ssd1680_adafruit_ssd1680", "callee": "malloc", "is_member_call": false, "source_file": "C:\\Users\\vince\\Projects\\PRNG\\.pio\\libdeps\\feather_m4\\Adafruit EPD\\src\\drivers\\Adafruit_SSD1680.cpp", "source_location": "L99"}, {"caller_nid": "drivers_adafruit_ssd1680_adafruit_ssd1680", "callee": "malloc", "is_member_call": false, "source_file": "C:\\Users\\vince\\Projects\\PRNG\\.pio\\libdeps\\feather_m4\\Adafruit EPD\\src\\drivers\\Adafruit_SSD1680.cpp", "source_location": "L100"}, {"caller_nid": "drivers_adafruit_ssd1680_busy_wait", "callee": "digitalRead", "is_member_call": false, "source_file": "C:\\Users\\vince\\Projects\\PRNG\\.pio\\libdeps\\feather_m4\\Adafruit EPD\\src\\drivers\\Adafruit_SSD1680.cpp", "source_location": "L113"}, {"caller_nid": "drivers_adafruit_ssd1680_busy_wait", "callee": "delay", "is_member_call": false, "source_file": "C:\\Users\\vince\\Projects\\PRNG\\.pio\\libdeps\\feather_m4\\Adafruit EPD\\src\\drivers\\Adafruit_SSD1680.cpp", "source_location": "L114"}, {"caller_nid": "drivers_adafruit_ssd1680_busy_wait", "callee": "delay", "is_member_call": false, "source_file": "C:\\Users\\vince\\Projects\\PRNG\\.pio\\libdeps\\feather_m4\\Adafruit EPD\\src\\drivers\\Adafruit_SSD1680.cpp", "source_location": "L117"}, {"caller_nid": "drivers_adafruit_ssd1680_begin", "callee": "setBlackBuffer", "is_member_call": false, "source_file": "C:\\Users\\vince\\Projects\\PRNG\\.pio\\libdeps\\feather_m4\\Adafruit EPD\\src\\drivers\\Adafruit_SSD1680.cpp", "source_location": "L129"}, {"caller_nid": "drivers_adafruit_ssd1680_begin", "callee": "setColorBuffer", "is_member_call": false, "source_file": "C:\\Users\\vince\\Projects\\PRNG\\.pio\\libdeps\\feather_m4\\Adafruit EPD\\src\\drivers\\Adafruit_SSD1680.cpp", "source_location": "L130"}, {"caller_nid": "drivers_adafruit_ssd1680_update", "callee": "EPD_command", "is_member_call": false, "source_file": "C:\\Users\\vince\\Projects\\PRNG\\.pio\\libdeps\\feather_m4\\Adafruit EPD\\src\\drivers\\Adafruit_SSD1680.cpp", "source_location": "L143"}, {"caller_nid": "drivers_adafruit_ssd1680_update", "callee": "EPD_command", "is_member_call": false, "source_file": "C:\\Users\\vince\\Projects\\PRNG\\.pio\\libdeps\\feather_m4\\Adafruit EPD\\src\\drivers\\Adafruit_SSD1680.cpp", "source_location": "L144"}, {"caller_nid": "drivers_adafruit_ssd1680_update", "callee": "delay", "is_member_call": false, "source_file": "C:\\Users\\vince\\Projects\\PRNG\\.pio\\libdeps\\feather_m4\\Adafruit EPD\\src\\drivers\\Adafruit_SSD1680.cpp", "source_location": "L148"}, {"caller_nid": "drivers_adafruit_ssd1680_powerup", "callee": "hardwareReset", "is_member_call": false, "source_file": "C:\\Users\\vince\\Projects\\PRNG\\.pio\\libdeps\\feather_m4\\Adafruit EPD\\src\\drivers\\Adafruit_SSD1680.cpp", "source_location": "L160"}, {"caller_nid": "drivers_adafruit_ssd1680_powerup", "callee": "delay", "is_member_call": false, "source_file": "C:\\Users\\vince\\Projects\\PRNG\\.pio\\libdeps\\feather_m4\\Adafruit EPD\\src\\drivers\\Adafruit_SSD1680.cpp", "source_location": "L161"}, {"caller_nid": "drivers_adafruit_ssd1680_powerup", "callee": "EPD_commandList", "is_member_call": false, "source_file": "C:\\Users\\vince\\Projects\\PRNG\\.pio\\libdeps\\feather_m4\\Adafruit EPD\\src\\drivers\\Adafruit_SSD1680.cpp", "source_location": "L169"}, {"caller_nid": "drivers_adafruit_ssd1680_powerup", "callee": "EPD_command", "is_member_call": false, "source_file": "C:\\Users\\vince\\Projects\\PRNG\\.pio\\libdeps\\feather_m4\\Adafruit EPD\\src\\drivers\\Adafruit_SSD1680.cpp", "source_location": "L179"}, {"caller_nid": "drivers_adafruit_ssd1680_powerup", "callee": "EPD_command", "is_member_call": false, "source_file": "C:\\Users\\vince\\Projects\\PRNG\\.pio\\libdeps\\feather_m4\\Adafruit EPD\\src\\drivers\\Adafruit_SSD1680.cpp", "source_location": "L186"}, {"caller_nid": "drivers_adafruit_ssd1680_powerup", "callee": "EPD_commandList", "is_member_call": false, "source_file": "C:\\Users\\vince\\Projects\\PRNG\\.pio\\libdeps\\feather_m4\\Adafruit EPD\\src\\drivers\\Adafruit_SSD1680.cpp", "source_location": "L190"}, {"caller_nid": "drivers_adafruit_ssd1680_powerup", "callee": "EPD_command", "is_member_call": false, "source_file": "C:\\Users\\vince\\Projects\\PRNG\\.pio\\libdeps\\feather_m4\\Adafruit EPD\\src\\drivers\\Adafruit_SSD1680.cpp", "source_location": "L197"}, {"caller_nid": "drivers_adafruit_ssd1680_powerdown", "callee": "EPD_command", "is_member_call": false, "source_file": "C:\\Users\\vince\\Projects\\PRNG\\.pio\\libdeps\\feather_m4\\Adafruit EPD\\src\\drivers\\Adafruit_SSD1680.cpp", "source_location": "L211"}, {"caller_nid": "drivers_adafruit_ssd1680_powerdown", "callee": "delay", "is_member_call": false, "source_file": "C:\\Users\\vince\\Projects\\PRNG\\.pio\\libdeps\\feather_m4\\Adafruit EPD\\src\\drivers\\Adafruit_SSD1680.cpp", "source_location": "L212"}, {"caller_nid": "drivers_adafruit_ssd1680_powerdown", "callee": "EPD_command", "is_member_call": false, "source_file": "C:\\Users\\vince\\Projects\\PRNG\\.pio\\libdeps\\feather_m4\\Adafruit EPD\\src\\drivers\\Adafruit_SSD1680.cpp", "source_location": "L214"}, {"caller_nid": "drivers_adafruit_ssd1680_writeramcommand", "callee": "EPD_command", "is_member_call": false, "source_file": "C:\\Users\\vince\\Projects\\PRNG\\.pio\\libdeps\\feather_m4\\Adafruit EPD\\src\\drivers\\Adafruit_SSD1680.cpp", "source_location": "L230"}, {"caller_nid": "drivers_adafruit_ssd1680_writeramcommand", "callee": "EPD_command", "is_member_call": false, "source_file": "C:\\Users\\vince\\Projects\\PRNG\\.pio\\libdeps\\feather_m4\\Adafruit EPD\\src\\drivers\\Adafruit_SSD1680.cpp", "source_location": "L233"}, {"caller_nid": "drivers_adafruit_ssd1680_setramaddress", "callee": "EPD_command", "is_member_call": false, "source_file": "C:\\Users\\vince\\Projects\\PRNG\\.pio\\libdeps\\feather_m4\\Adafruit EPD\\src\\drivers\\Adafruit_SSD1680.cpp", "source_location": "L253"}, {"caller_nid": "drivers_adafruit_ssd1680_setramaddress", "callee": "EPD_command", "is_member_call": false, "source_file": "C:\\Users\\vince\\Projects\\PRNG\\.pio\\libdeps\\feather_m4\\Adafruit EPD\\src\\drivers\\Adafruit_SSD1680.cpp", "source_location": "L258"}]}