{
  "nodes": [
    {
      "id": "Adafruit_HX8357",
      "label": "Adafruit HX8357",
      "file_type": "code",
      "source_file": "Adafruit_HX8357.cpp",
      "source_location": null,
      "source_url": null,
      "captured_at": null,
      "author": "Limor Fried/Ladyada",
      "contributor": null
    },
    {
      "id": "filter_detect",
      "label": "Filter Detect Script",
      "file_type": "code",
      "source_file": "filter_detect.py",
      "source_location": null,
      "source_url": null,
      "captured_at": null,
      "author": null,
      "contributor": null
    },
    {
      "id": "get_stats",
      "label": "Get Stats Script",
      "file_type": "code",
      "source_file": "get_stats.py",
      "source_location": null,
      "source_url": null,
      "captured_at": null,
      "author": null,
      "contributor": null
    },
    {
      "id": "convert_init",
      "label": "Convert Init Script",
      "file_type": "code",
      "source_file": "scripts/convert_init.py",
      "source_location": null,
      "source_url": null,
      "captured_at": null,
      "author": null,
      "contributor": null
    },
    {
      "id": "write_init",
      "label": "Write Init Script",
      "file_type": "code",
      "source_file": "scripts/write_init.py",
      "source_location": null,
      "source_url": null,
      "captured_at": null,
      "author": null,
      "contributor": null
    },
    {
      "id": "bram_framebuffer",
      "label": "BRAM Framebuffer",
      "file_type": "code",
      "source_file": "verilog/src/bram_framebuffer.v",
      "source_location": null,
      "source_url": null,
      "captured_at": null,
      "author": null,
      "contributor": null
    },
    {
      "id": "game_of_life",
      "label": "Game Of Life Hardware",
      "file_type": "code",
      "source_file": "verilog/src/game_of_life.v",
      "source_location": null,
      "source_url": null,
      "captured_at": null,
      "author": null,
      "contributor": null
    },
    {
      "id": "hx8357d_controller",
      "label": "HX8357D Controller",
      "file_type": "code",
      "source_file": "verilog/src/hx8357d_controller.v",
      "source_location": null,
      "source_url": null,
      "captured_at": null,
      "author": null,
      "contributor": null
    },
    {
      "id": "hx8357d_init",
      "label": "HX8357D Init",
      "file_type": "code",
      "source_file": "verilog/src/hx8357d_init.v",
      "source_location": null,
      "source_url": null,
      "captured_at": null,
      "author": null,
      "contributor": null
    },
    {
      "id": "tb_game_of_life",
      "label": "Testbench Game Of Life",
      "file_type": "code",
      "source_file": "verilog/testbench/tb_game_of_life.v",
      "source_location": null,
      "source_url": null,
      "captured_at": null,
      "author": null,
      "contributor": null
    },
    {
      "id": "tb_hx8357d_controller",
      "label": "Testbench HX8357D Controller",
      "file_type": "code",
      "source_file": "verilog/testbench/tb_hx8357d_controller.v",
      "source_location": null,
      "source_url": null,
      "captured_at": null,
      "author": null,
      "contributor": null
    },
    {
      "id": "uart_loopback",
      "label": "UART Loopback",
      "file_type": "code",
      "source_file": "_archive/uart_loopback.v",
      "source_location": null,
      "source_url": null,
      "captured_at": null,
      "author": null,
      "contributor": null
    },
    {
      "id": "diagnostic_test",
      "label": "Diagnostic Test",
      "file_type": "code",
      "source_file": "_archive_disabled/diagnostic_test.cpp",
      "source_location": null,
      "source_url": null,
      "captured_at": null,
      "author": null,
      "contributor": null
    },
    {
      "id": "graphify_skill",
      "label": "Graphify Skill",
      "file_type": "rationale",
      "source_file": ".agents/skills/graphify/SKILL.md",
      "source_location": null,
      "source_url": null,
      "captured_at": null,
      "author": null,
      "contributor": null
    },
    {
      "id": "fingerprint_data_collection_guide",
      "label": "Fingerprint Data Collection Guide",
      "file_type": "document",
      "source_file": "esp32_fingerprint/FINGERPRINT_DATA_COLLECTION_GUIDE.txt",
      "source_location": null,
      "source_url": null,
      "captured_at": null,
      "author": null,
      "contributor": null
    },
    {
      "id": "fingerprint_data_analysis",
      "label": "Fingerprint Data Analysis",
      "file_type": "document",
      "source_file": "fingerprints/fingerprint_data_analysis.txt",
      "source_location": null,
      "source_url": null,
      "captured_at": null,
      "author": null,
      "contributor": null
    },
    {
      "id": "validation_report",
      "label": "Validation Report",
      "file_type": "document",
      "source_file": "fingerprints/validation_report.txt",
      "source_location": null,
      "source_url": null,
      "captured_at": null,
      "author": null,
      "contributor": null
    },
    {
      "id": "converted_utf8_txt",
      "label": "Converted Initialization Values",
      "file_type": "document",
      "source_file": "scripts/converted_utf8.txt",
      "source_location": null,
      "source_url": null,
      "captured_at": null,
      "author": null,
      "contributor": null
    },
    {
      "id": "quick_start_guide",
      "label": "Quick Start Guide",
      "file_type": "document",
      "source_file": "verilog/QUICK_START.md",
      "source_location": null,
      "source_url": null,
      "captured_at": null,
      "author": null,
      "contributor": null
    },
    {
      "id": "usage_guide",
      "label": "Usage Guide",
      "file_type": "document",
      "source_file": "verilog/USAGE.md",
      "source_location": null,
      "source_url": null,
      "captured_at": null,
      "author": null,
      "contributor": null
    },
    {
      "id": "testbench_readme",
      "label": "Testbench README",
      "file_type": "document",
      "source_file": "verilog/testbench/README.md",
      "source_location": null,
      "source_url": null,
      "captured_at": null,
      "author": null,
      "contributor": null
    },
    {
      "id": "Adafruit_SPITFT",
      "label": "Adafruit SPITFT",
      "file_type": "code",
      "source_file": "Adafruit_HX8357.h",
      "source_location": null,
      "source_url": null,
      "captured_at": null,
      "author": null,
      "contributor": null
    },
    {
      "id": "spi_master",
      "label": "SPI Master",
      "file_type": "code",
      "source_file": "verilog/src/hx8357d_controller.v",
      "source_location": null,
      "source_url": null,
      "captured_at": null,
      "author": null,
      "contributor": null
    }
  ],
  "edges": [
    {
      "source": "convert_init",
      "target": "write_init",
      "relation": "conceptually_related_to",
      "confidence": "INFERRED",
      "confidence_score": 0.85,
      "source_file": "scripts/convert_init.py",
      "source_location": null,
      "weight": 1.0
    },
    {
      "source": "write_init",
      "target": "hx8357d_init",
      "relation": "conceptually_related_to",
      "confidence": "INFERRED",
      "confidence_score": 0.95,
      "source_file": "scripts/write_init.py",
      "source_location": null,
      "weight": 1.0
    },
    {
      "source": "convert_init",
      "target": "Adafruit_HX8357",
      "relation": "shares_data_with",
      "confidence": "INFERRED",
      "confidence_score": 0.85,
      "source_file": "scripts/convert_init.py",
      "source_location": null,
      "weight": 1.0
    },
    {
      "source": "hx8357d_controller",
      "target": "game_of_life",
      "relation": "calls",
      "confidence": "EXTRACTED",
      "confidence_score": 1.0,
      "source_file": "verilog/src/hx8357d_controller.v",
      "source_location": null,
      "weight": 1.0
    },
    {
      "source": "hx8357d_controller",
      "target": "bram_framebuffer",
      "relation": "calls",
      "confidence": "EXTRACTED",
      "confidence_score": 1.0,
      "source_file": "verilog/src/hx8357d_controller.v",
      "source_location": null,
      "weight": 1.0
    },
    {
      "source": "hx8357d_controller",
      "target": "spi_master",
      "relation": "calls",
      "confidence": "EXTRACTED",
      "confidence_score": 1.0,
      "source_file": "verilog/src/hx8357d_controller.v",
      "source_location": null,
      "weight": 1.0
    },
    {
      "source": "hx8357d_controller",
      "target": "hx8357d_init",
      "relation": "calls",
      "confidence": "EXTRACTED",
      "confidence_score": 1.0,
      "source_file": "verilog/src/hx8357d_controller.v",
      "source_location": null,
      "weight": 1.0
    },
    {
      "source": "tb_game_of_life",
      "target": "game_of_life",
      "relation": "calls",
      "confidence": "EXTRACTED",
      "confidence_score": 1.0,
      "source_file": "verilog/testbench/tb_game_of_life.v",
      "source_location": null,
      "weight": 1.0
    },
    {
      "source": "tb_game_of_life",
      "target": "bram_framebuffer",
      "relation": "calls",
      "confidence": "EXTRACTED",
      "confidence_score": 1.0,
      "source_file": "verilog/testbench/tb_game_of_life.v",
      "source_location": null,
      "weight": 1.0
    },
    {
      "source": "tb_hx8357d_controller",
      "target": "hx8357d_controller",
      "relation": "calls",
      "confidence": "EXTRACTED",
      "confidence_score": 1.0,
      "source_file": "verilog/testbench/tb_hx8357d_controller.v",
      "source_location": null,
      "weight": 1.0
    },
    {
      "source": "game_of_life",
      "target": "bram_framebuffer",
      "relation": "references",
      "confidence": "INFERRED",
      "confidence_score": 0.95,
      "source_file": "verilog/src/game_of_life.v",
      "source_location": null,
      "weight": 1.0
    },
    {
      "source": "diagnostic_test",
      "target": "game_of_life",
      "relation": "calls",
      "confidence": "INFERRED",
      "confidence_score": 0.65,
      "source_file": "_archive_disabled/diagnostic_test.cpp",
      "source_location": null,
      "weight": 1.0
    },
    {
      "source": "Adafruit_HX8357",
      "target": "Adafruit_SPITFT",
      "relation": "implements",
      "confidence": "EXTRACTED",
      "confidence_score": 1.0,
      "source_file": "Adafruit_HX8357.h",
      "source_location": null,
      "weight": 1.0
    },
    {
      "source": "fingerprint_data_collection_guide",
      "target": "fingerprint_data_analysis",
      "relation": "conceptually_related_to",
      "confidence": "INFERRED",
      "confidence_score": 0.85,
      "source_file": "esp32_fingerprint/FINGERPRINT_DATA_COLLECTION_GUIDE.txt",
      "source_location": null,
      "weight": 1.0
    },
    {
      "source": "fingerprint_data_analysis",
      "target": "validation_report",
      "relation": "conceptually_related_to",
      "confidence": "INFERRED",
      "confidence_score": 0.85,
      "source_file": "fingerprints/fingerprint_data_analysis.txt",
      "source_location": null,
      "weight": 1.0
    },
    {
      "source": "quick_start_guide",
      "target": "usage_guide",
      "relation": "conceptually_related_to",
      "confidence": "INFERRED",
      "confidence_score": 0.95,
      "source_file": "verilog/QUICK_START.md",
      "source_location": null,
      "weight": 1.0
    },
    {
      "source": "write_init",
      "target": "converted_utf8_txt",
      "relation": "conceptually_related_to",
      "confidence": "INFERRED",
      "confidence_score": 0.75,
      "source_file": "scripts/write_init.py",
      "source_location": null,
      "weight": 1.0
    }
  ],
  "hyperedges": [
    {
      "id": "hx8357d_init_group",
      "label": "HX8357D Initialization Translation",
      "nodes": [
        "Adafruit_HX8357",
        "convert_init",
        "write_init",
        "hx8357d_init",
        "converted_utf8_txt"
      ],
      "relation": "participate_in",
      "confidence": "INFERRED",
      "confidence_score": 0.85,
      "source_file": "scripts/write_init.py"
    },
    {
      "id": "game_of_life_hardware",
      "label": "Game of Life Hardware Implementation",
      "nodes": [
        "hx8357d_controller",
        "game_of_life",
        "bram_framebuffer"
      ],
      "relation": "participate_in",
      "confidence": "INFERRED",
      "confidence_score": 0.85,
      "source_file": "verilog/src/hx8357d_controller.v"
    },
    {
      "id": "fingerprint_analysis",
      "label": "Fingerprint Data Validation",
      "nodes": [
        "fingerprint_data_collection_guide",
        "fingerprint_data_analysis",
        "validation_report"
      ],
      "relation": "form",
      "confidence": "INFERRED",
      "confidence_score": 0.85,
      "source_file": "fingerprints/fingerprint_data_analysis.txt"
    }
  ],
  "input_tokens": 0,
  "output_tokens": 0
}
